inverse_projections/__init__.py
inverse_projections/gradient_map.py
inverse_projections/lamp.py
inverse_projections/multilateration.py
inverse_projections/nninv.py
inverse_projections/rbf.py
inverse_projections-0.1.3.dist-info/WHEEL
inverse_projections-0.1.3.dist-info/entry_points.txt
inverse_projections-0.1.3.dist-info/METADATA
inverse_projections-0.1.3.dist-info/RECORD
